<annotation>
	<folder>New folder</folder>
	<filename>avocado-3.jpg</filename>
	<path>E:\labelImg-master\New folder\avocado-3.jpg</path>
	<source>
		<database>Unknown</database>
	</source>
	<size>
		<width>2560</width>
		<height>1920</height>
		<depth>3</depth>
	</size>
	<segmented>0</segmented>
	<object>
		<name>avocado</name>
		<pose>Unspecified</pose>
		<truncated>0</truncated>
		<difficult>0</difficult>
		<bndbox>
			<xmin>239</xmin>
			<ymin>1051</ymin>
			<xmax>558</xmax>
			<ymax>1559</ymax>
		</bndbox>
	</object>
	<object>
		<name>avocado</name>
		<pose>Unspecified</pose>
		<truncated>0</truncated>
		<difficult>0</difficult>
		<bndbox>
			<xmin>1027</xmin>
			<ymin>435</ymin>
			<xmax>1364</xmax>
			<ymax>910</ymax>
		</bndbox>
	</object>
	<object>
		<name>avocado</name>
		<pose>Unspecified</pose>
		<truncated>0</truncated>
		<difficult>0</difficult>
		<bndbox>
			<xmin>1541</xmin>
			<ymin>363</ymin>
			<xmax>1837</xmax>
			<ymax>898</ymax>
		</bndbox>
	</object>
	<object>
		<name>avocado</name>
		<pose>Unspecified</pose>
		<truncated>0</truncated>
		<difficult>0</difficult>
		<bndbox>
			<xmin>1898</xmin>
			<ymin>696</ymin>
			<xmax>2284</xmax>
			<ymax>1270</ymax>
		</bndbox>
	</object>
	<object>
		<name>avocado</name>
		<pose>Unspecified</pose>
		<truncated>0</truncated>
		<difficult>0</difficult>
		<bndbox>
			<xmin>1494</xmin>
			<ymin>935</ymin>
			<xmax>2352</xmax>
			<ymax>1678</ymax>
		</bndbox>
	</object>
	<object>
		<name>avocado</name>
		<pose>Unspecified</pose>
		<truncated>0</truncated>
		<difficult>0</difficult>
		<bndbox>
			<xmin>982</xmin>
			<ymin>1131</ymin>
			<xmax>1423</xmax>
			<ymax>1719</ymax>
		</bndbox>
	</object>
</annotation>
